{
  "main": {
    "id": "1694fcfb087acaa2",
    "type": "split",
    "children": [
      {
        "id": "82c12ff67d9ff154",
        "type": "tabs",
        "children": [
          {
            "id": "b405b83700338e6a",
            "type": "leaf",
            "state": {
              "type": "markdown",
              "state": {
                "file": "Hello Algo/No12. 分治/12.2 分治搜索策略.md",
                "mode": "source",
                "source": false
              }
            }
          },
          {
            "id": "39a9385c03f2c117",
            "type": "leaf",
            "state": {
              "type": "markdown",
              "state": {
                "file": "Hello Algo/No12. 分治/12.3 构建二叉树问题.md",
                "mode": "source",
                "source": false
              }
            }
          },
          {
            "id": "d89b910ca0b60c05",
            "type": "leaf",
            "state": {
              "type": "markdown",
              "state": {
                "file": "Hello Algo/No12. 分治/12.4 汉诺塔问题.md",
                "mode": "source",
                "source": false
              }
            }
          },
          {
            "id": "f7ee60799cb38a9f",
            "type": "leaf",
            "state": {
              "type": "markdown",
              "state": {
                "file": "Hello Algo/No12. 分治/12.5 分治小结.md",
                "mode": "source",
                "source": false
              }
            }
          },
          {
            "id": "5a564211db19b8ba",
            "type": "leaf",
            "state": {
              "type": "markdown",
              "state": {
                "file": "Hello Algo/No12. 分治/12.1 分治算法.md",
                "mode": "source",
                "source": false
              }
            }
          },
          {
            "id": "496f3c24054098ff",
            "type": "leaf",
            "state": {
              "type": "markdown",
              "state": {
                "file": "Hello Algo/No11. 排序/11.6 归并排序.md",
                "mode": "source",
                "source": false
              }
            }
          },
          {
            "id": "d22582923ec1666d",
            "type": "leaf",
            "state": {
              "type": "markdown",
              "state": {
                "file": "Hello Algo/No11. 排序/11.7 堆排序.md",
                "mode": "source",
                "source": false
              }
            }
          }
        ],
        "currentTab": 1
      }
    ],
    "direction": "vertical"
  },
  "left": {
    "id": "8296ae919af5a195",
    "type": "split",
    "children": [
      {
        "id": "7e3545dacb4d9a9d",
        "type": "tabs",
        "children": [
          {
            "id": "887475e7de336b95",
            "type": "leaf",
            "state": {
              "type": "file-explorer",
              "state": {
                "sortOrder": "alphabetical"
              }
            }
          },
          {
            "id": "e2b9adc560c659e3",
            "type": "leaf",
            "state": {
              "type": "search",
              "state": {
                "query": "",
                "matchingCase": false,
                "explainSearch": false,
                "collapseAll": false,
                "extraContext": false,
                "sortOrder": "alphabetical"
              }
            }
          },
          {
            "id": "90c6d970f540e9fe",
            "type": "leaf",
            "state": {
              "type": "bookmarks",
              "state": {}
            }
          },
          {
            "id": "fa27e3614b8f25b9",
            "type": "leaf",
            "state": {
              "type": "tag",
              "state": {
                "sortOrder": "frequency",
                "useHierarchy": true
              }
            }
          },
          {
            "id": "4f0ca8bc7ee868ca",
            "type": "leaf",
            "state": {
              "type": "recent-files",
              "state": {}
            }
          },
          {
            "id": "0faa49b53cf1873b",
            "type": "leaf",
            "state": {
              "type": "calendar",
              "state": {}
            }
          }
        ]
      }
    ],
    "direction": "horizontal",
    "width": 304.5004348754883
  },
  "right": {
    "id": "5b4044efa7af0982",
    "type": "split",
    "children": [
      {
        "id": "b54f69180a550e99",
        "type": "tabs",
        "children": [
          {
            "id": "5c4221ccd969383c",
            "type": "leaf",
            "state": {
              "type": "backlink",
              "state": {
                "file": "Hello Algo/No12. 分治/12.2 分治搜索策略.md",
                "collapseAll": false,
                "extraContext": false,
                "sortOrder": "alphabetical",
                "showSearch": false,
                "searchQuery": "",
                "backlinkCollapsed": false,
                "unlinkedCollapsed": true
              }
            }
          },
          {
            "id": "3f26895bc9698697",
            "type": "leaf",
            "state": {
              "type": "outgoing-link",
              "state": {
                "file": "Hello Algo/No12. 分治/12.2 分治搜索策略.md",
                "linksCollapsed": false,
                "unlinkedCollapsed": true
              }
            }
          },
          {
            "id": "140ebb0227b05852",
            "type": "leaf",
            "state": {
              "type": "outline",
              "state": {
                "file": "Hello Algo/No12. 分治/12.2 分治搜索策略.md"
              }
            }
          },
          {
            "id": "21d6779bb06edb07",
            "type": "leaf",
            "state": {
              "type": "advanced-tables-toolbar",
              "state": {}
            }
          }
        ],
        "currentTab": 2
      }
    ],
    "direction": "horizontal",
    "width": 284.5,
    "collapsed": true
  },
  "left-ribbon": {
    "hiddenItems": {
      "switcher:打开快速切换": false,
      "graph:查看关系图谱": false,
      "omnisearch:Omnisearch": false,
      "command-palette:打开命令面板": false,
      "canvas:新建白板": false,
      "daily-notes:打开/创建今天的日记": false,
      "templates:插入模板": false,
      "table-editor-obsidian:Advanced Tables Toolbar": false,
      "obsidian-excalidraw-plugin:新建绘图文件": false,
      "obsidian-kanban:创建新看板": false,
      "templater-obsidian:Templater": false,
      "obsidian-advanced-slides:Show Slide Preview": false
    }
  },
  "active": "887475e7de336b95",
  "lastOpenFiles": [
    "Hello Algo/No12. 分治/12.1 分治算法.md",
    "Hello Algo/No11. 排序/11.7 堆排序.md",
    "Hello Algo/No11. 排序/11.6 归并排序.md",
    "Hello Algo/No12. 分治/12.2 分治搜索策略.md",
    "Hello Algo/No12. 分治/12.5 分治小结.md",
    "Hello Algo/No12. 分治/12.4 汉诺塔问题.md",
    "ObsidianImages/Pasted image 20240605171124.png",
    "ObsidianImages/Pasted image 20240605171041.png",
    "ObsidianImages/Pasted image 20240605170940.png",
    "ObsidianImages/Pasted image 20240605170936.png",
    "ObsidianImages/Pasted image 20240605170921.png",
    "ObsidianImages/Pasted image 20240605170915.png",
    "ObsidianImages/Pasted image 20240605170820.png",
    "ObsidianImages/Pasted image 20240605170811.png",
    "ObsidianImages/Pasted image 20240605170749.png",
    "ObsidianImages/Pasted image 20240605170741.png",
    "Hello Algo/No12. 分治/12.3 构建二叉树问题.md",
    "Hello Algo/No11. 排序/11.11 排序小结.md",
    "Hello Algo/No12. 分治",
    "Hello Algo/No11. 排序/11.10 基数排序.md",
    "Hello Algo/No11. 排序/11.9 计数排序.md",
    "Hello Algo/No11. 排序/11.8 桶排序.md",
    "Hello Algo/No8. 堆/8.2 建堆操作.md",
    "Hello Algo/No11. 排序/11.5 快速排序.md",
    "Hello Algo/No11. 排序/11.4 插入排序.md",
    "labuladong 的算法笔记/核心架构汇总/双指针技巧秒杀七道数组题目.md",
    "labuladong 的算法笔记/数据结构刷题/刷链表算法/双指针技巧秒杀七道链表题目.md",
    "labuladong 的算法笔记/数据结构刷题/刷链表算法/递归魔法：反转单链表.md",
    "Hello Algo/No10. 搜索/10.1 二分查找.md",
    "Hello Algo/No11. 排序/11.3 冒泡排序.md",
    "Hello Algo/No11. 排序/11.2 选择排序.md",
    "Hello Algo/No11. 排序/11.1 排序算法.md",
    "Hello Algo/No10. 搜索/10.6 搜索小结.md",
    "Hello Algo/No10. 搜索/10.5 重识搜索算法.md",
    "Hello Algo/No10. 搜索/10.4 哈希优化策略.md",
    "Hello Algo/No10. 搜索/10.3 二分查找边界.md",
    "Hello Algo/No10. 搜索/10.2 二分查找插入点.md",
    "Hello Algo/No11. 排序",
    "Hello Algo/No10. 搜索",
    "labuladong 的算法笔记/数据结构刷题/刷链表算法",
    "Hello Algo/No9. 图",
    "labuladong 的算法笔记/数据结构刷题",
    "labuladong 的算法笔记/核心架构汇总",
    "labuladong 的算法笔记",
    "Hello Algo/No8. 堆",
    "Hello Algo/No7. 树",
    "数据平台工程师面试汇总/未命名.canvas"
  ]
}